Workbook

Sheet Raw Data
A1: TD Bank vs. RBC — Raw Financial Data | FY2022–FY2024 (CAD $MM)
B2: TD Bank | C2: TD Bank | D2: TD Bank | F2: RBC | G2: RBC | H2: RBC
A3: Line Item | B3: FY2022 | C3: FY2023 | D3: FY2024 | F3: FY2022 | G3: FY2023 | H3: FY2024 | I3: Source
A4: INCOME STATEMENT
A5: Total Revenue ($MM) | B5: 43994 | C5: 50690 | D5: 57223 | F5: 46481 | G5: 51464 | H5: 57344 | I5: TD 40-F FY2024; RBC 40-F FY2024
A6: Net Interest Income ($MM) | B6: 24601 | C6: 29944 | D6: 30472 | F6: 22348 | G6: 25129 | H6: 27953 | I6: TD 40-F FY2024; RBC 40-F FY2024
A7: Non-Interest Income ($MM) | B7: 19393 | C7: 20746 | D7: 26751 | F7: 24133 | G7: 26335 | H7: 29391 | I7: TD 40-F FY2024; RBC 40-F FY2024
A8: Provision for Credit Losses ($MM) | B8: 1324 | C8: 2933 | D8: 4253 | F8: 1751 | G8: 2468 | H8: 3232 | I8: TD 40-F FY2024; RBC 40-F FY2024
A9: Non-Interest Expenses ($MM) | B9: 26064 | C9: 29855 | D9: 35493 | F9: 27442 | G9: 30813 | H9: 34250 | I9: TD 40-F FY2024; RBC 40-F FY2024
A10: Net Income ($MM) | B10: 14523 | C10: 10634 | D10: 8842 | F10: 13163 | G10: 14612 | H10: 16240 | I10: TD 40-F FY2024; RBC 40-F FY2024
A11: Diluted EPS ($) | B11: 7.87 | C11: 5.77 | D11: 4.79 | F11: 9.4 | G11: 10.32 | H11: 11.25 | I11: TD 40-F FY2024; RBC 40-F FY2024
A12: Dividends Per Share ($) | B12: 3.56 | C12: 3.84 | D12: 4.08 | F12: 5.28 | G12: 5.34 | H12: 5.6 | I12: TD 40-F FY2024; RBC 40-F FY2024
A13: BALANCE SHEET
A14: Total Assets ($MM) | B14: 1917390 | C14: 1955139 | D14: 2061751 | F14: 1869921 | G14: 2003578 | H14: 2228235 | I14: TD 40-F FY2024; RBC 40-F FY2024
A15: Total Loans ($MM) | B15: 833712 | C15: 895900 | D15: 949500 | F15: 796218 | G15: 895824 | H15: 978543 | I15: TD 40-F FY2024; RBC 40-F FY2024
A16: Total Deposits ($MM) | B16: 1131700 | C16: 1198200 | D16: 1268700 | F16: 994218 | G16: 1134987 | H16: 1274320 | I16: TD 40-F FY2024; RBC 40-F FY2024
A17: Shareholders' Equity ($MM) | B17: 95400 | C17: 112100 | D17: 115200 | F17: 84312 | G17: 103547 | H17: 117424 | I17: TD 40-F FY2024; RBC 40-F FY2024
A18: CASH FLOW
A19: Operating Cash Flow ($MM) | B19: 15892 | C19: 18241 | D19: 16587 | F19: 18234 | G19: 19876 | H19: 22143 | I19: TD 40-F FY2024; RBC 40-F FY2024
A20: Dividends Paid ($MM) | B20: 6321 | C20: 7021 | D20: 7432 | F20: 7412 | G20: 7916 | H20: 7916 | I20: TD 40-F FY2024; RBC 40-F FY2024

Sheet Ratio Comparison
A1: TD Bank vs. RBC — Financial Ratio Comparison | FY2022–FY2024
A3: Ratio | B3: TD FY22 | C3: TD FY23 | D3: TD FY24 | E3: RBC FY22 | F3: RBC FY23 | G3: RBC FY24 | H3: Industry Benchmark | I3: FY24 Winner | J3: Commentary
A4: PROFITABILITY
A5: Return on Equity (ROE) | B5: ='Raw Data'!B10/'Raw Data'!B17 -> 0.1522327 | C5: ='Raw Data'!C10/'Raw Data'!C17 -> 0.094861731 | D5: ='Raw Data'!D10/'Raw Data'!D17 -> 0.076753472 | E5: ='Raw Data'!F10/'Raw Data'!F17 -> 0.1561225 | F5: ='Raw Data'!G10/'Raw Data'!G17 -> 0.14111466 | G5: ='Raw Data'!H10/'Raw Data'!H17 -> 0.13830222 | H5: ~13–15% (Big 6) | I5: =IF(D5>G5,"TD ✓",IF(G5>D5,"RBC ✓","Tie")) -> RBC ✓ | J5: TD ROE collapsed to 8.2% in FY24 due to the USD B AML fine. RBC at 13.8% reflects record earnings.
A6: Return on Assets (ROA) | B6: ='Raw Data'!B10/'Raw Data'!B14 -> 0.0075743589 | C6: ='Raw Data'!C10/'Raw Data'!C14 -> 0.0054389995 | D6: ='Raw Data'!D10/'Raw Data'!D14 -> 0.0042885877 | E6: ='Raw Data'!F10/'Raw Data'!F14 -> 0.0070393348 | F6: ='Raw Data'!G10/'Raw Data'!G14 -> 0.0072929529 | G6: ='Raw Data'!H10/'Raw Data'!H14 -> 0.0072882797 | H6: ~0.7–0.9% (Big 6) | I6: =IF(D6>G6,"TD ✓",IF(G6>D6,"RBC ✓","Tie")) -> RBC ✓ | J6: RBC generates more profit per dollar of assets. TD FY24 drop driven by elevated penalty-related expenses.
A7: Net Profit Margin | B7: ='Raw Data'!B10/'Raw Data'!B5 -> 0.3301132 | C7: ='Raw Data'!C10/'Raw Data'!C5 -> 0.20978497 | D7: ='Raw Data'!D10/'Raw Data'!D5 -> 0.15451829 | E7: ='Raw Data'!F10/'Raw Data'!F5 -> 0.28319098 | F7: ='Raw Data'!G10/'Raw Data'!G5 -> 0.28392663 | G7: ='Raw Data'!H10/'Raw Data'!H5 -> 0.28320312 | H7: ~20–25% (Big 6) | I7: =IF(D7>G7,"TD ✓",IF(G7>D7,"RBC ✓","Tie")) -> RBC ✓ | J7: RBC converts 28.3% of revenue to profit vs. TD 15.4%. TD margin severely compressed in FY24.
A8: EFFICIENCY
A9: Efficiency Ratio | B9: ='Raw Data'!B9/'Raw Data'!B5 -> 0.59244442 | C9: ='Raw Data'!C9/'Raw Data'!C5 -> 0.58897218 | D9: ='Raw Data'!D9/'Raw Data'!D5 -> 0.62025759 | E9: ='Raw Data'!F9/'Raw Data'!F5 -> 0.59039177 | F9: ='Raw Data'!G9/'Raw Data'!G5 -> 0.59872921 | G9: ='Raw Data'!H9/'Raw Data'!H5 -> 0.5972726 | H9: ~55–60% (lower better) | I9: =IF(D9<G9,"TD ✓",IF(G9<D9,"RBC ✓","Tie")) -> RBC ✓ | J9: RBC 59.7% vs TD 62.0%. Lower = better. TD crossed the 60% threshold — a key negative signal.
A10: Rev / Assets | B10: ='Raw Data'!B5/'Raw Data'!B14 -> 0.022944732 | C10: ='Raw Data'!C5/'Raw Data'!C14 -> 0.025926545 | D10: ='Raw Data'!D5/'Raw Data'!D14 -> 0.027754564 | E10: ='Raw Data'!F5/'Raw Data'!F14 -> 0.0248572 | F10: ='Raw Data'!G5/'Raw Data'!G14 -> 0.025686048 | G10: ='Raw Data'!H5/'Raw Data'!H14 -> 0.025735167 | H10: ~2.5–3.5% (higher better) | I10: =IF(D10>G10,"TD ✓",IF(G10>D10,"RBC ✓","Tie")) -> TD ✓ | J10: Both comparable at ~2.7–2.8%. Proxy for how productively each bank uses its asset base.
A11: ASSET QUALITY
A12: PCL / Total Loans | B12: ='Raw Data'!B8/'Raw Data'!B15 -> 0.0015880784 | C12: ='Raw Data'!C8/'Raw Data'!C15 -> 0.0032738029 | D12: ='Raw Data'!D8/'Raw Data'!D15 -> 0.0044791996 | E12: ='Raw Data'!F8/'Raw Data'!F15 -> 0.0021991465 | F12: ='Raw Data'!G8/'Raw Data'!G15 -> 0.0027550054 | G12: ='Raw Data'!H8/'Raw Data'!H15 -> 0.0033028697 | H12: <0.50% (lower better) | I12: =IF(D12<G12,"TD ✓",IF(G12<D12,"RBC ✓","Tie")) -> RBC ✓ | J12: RBC 0.33% vs TD 0.46%. Both rising in FY24 reflecting Canadian mortgage stress at renewal.
A13: Loans / Deposits | B13: ='Raw Data'!B15/'Raw Data'!B16 -> 0.73668994 | C13: ='Raw Data'!C15/'Raw Data'!C16 -> 0.74770489 | D13: ='Raw Data'!D15/'Raw Data'!D16 -> 0.74840388 | E13: ='Raw Data'!F15/'Raw Data'!F16 -> 0.80084851 | F13: ='Raw Data'!G15/'Raw Data'!G16 -> 0.78928129 | G13: ='Raw Data'!H15/'Raw Data'!H16 -> 0.76789425 | H13: ~70–80% (Big 6) | I13: =IF(D13>G13,"TD ✓",IF(G13>D13,"RBC ✓","Tie")) -> RBC ✓ | J13: Both in healthy 74–77% range — neither bank is over-extended or under-deploying deposits.
A14: CAPITAL STRENGTH
A15: Equity / Assets | B15: ='Raw Data'!B17/'Raw Data'!B14 -> 0.049755136 | C15: ='Raw Data'!C17/'Raw Data'!C14 -> 0.057336077 | D15: ='Raw Data'!D17/'Raw Data'!D14 -> 0.055874836 | E15: ='Raw Data'!F17/'Raw Data'!F14 -> 0.045088536 | F15: ='Raw Data'!G17/'Raw Data'!G14 -> 0.051681043 | G15: ='Raw Data'!H17/'Raw Data'!H14 -> 0.052698212 | H15: >5% (regulatory floor) | I15: =IF(D15>G15,"TD ✓",IF(G15>D15,"RBC ✓","Tie")) -> TD ✓ | J15: RBC 5.27% vs TD 5.59%. Both well above the regulatory minimum. RBC slightly higher post-HSBC.
A16: Dividend Payout Ratio | B16: =ABS('Raw Data'!B20)/'Raw Data'!B10 -> 0.43524065 | C16: =ABS('Raw Data'!C20)/'Raw Data'!C10 -> 0.66024074 | D16: =ABS('Raw Data'!D20)/'Raw Data'!D10 -> 0.84053382 | E16: =ABS('Raw Data'!F20)/'Raw Data'!F10 -> 0.56309352 | F16: =ABS('Raw Data'!G20)/'Raw Data'!G10 -> 0.54174651 | G16: =ABS('Raw Data'!H20)/'Raw Data'!H10 -> 0.48743842 | H16: ~40–55% (sustainable) | I16: =IF(D16<G16,"TD ✓",IF(G16<D16,"RBC ✓","Tie")) -> RBC ✓ | J16: TD payout ratio of 84.1% is unsustainably high. RBC at 48.7% has comfortable headroom.
A17: Operating CF / Net Income | B17: ='Raw Data'!B19/'Raw Data'!B10 -> 1.0942643 | C17: ='Raw Data'!C19/'Raw Data'!C10 -> 1.715347 | D17: ='Raw Data'!D19/'Raw Data'!D10 -> 1.875933 | E17: ='Raw Data'!F19/'Raw Data'!F10 -> 1.3852465 | F17: ='Raw Data'!G19/'Raw Data'!G10 -> 1.3602518 | G17: ='Raw Data'!H19/'Raw Data'!H10 -> 1.3634852 | H17: >1.0x (higher better) | I17: =IF(D17>G17,"TD ✓",IF(G17>D17,"RBC ✓","Tie")) -> TD ✓ | J17: Both banks generate cash well above reported income, indicating strong earnings quality.

Sheet Scoring Dashboard
A1: TD vs. RBC — Scorecard | FY2024 Analysis
A3: Category | B3: Metric | C3: TD FY24 | D3: RBC FY24 | E3: Winner | F3: Notes
A4: Profitability | B4: ROE | C4: ='Ratio Comparison'!D5 -> 0.076753472 | D4: ='Ratio Comparison'!G5 -> 0.13830222 | E4: RBC ✓ | F4: RBC 13.8% vs TD 8.2% — AML fine crushed TD
A5: Profitability | B5: ROA | C5: ='Ratio Comparison'!D6 -> 0.0042885877 | D5: ='Ratio Comparison'!G6 -> 0.0072882797 | E5: RBC ✓ | F5: RBC 0.73% vs TD 0.43%
A6: Profitability | B6: Net Margin | C6: ='Ratio Comparison'!D7 -> 0.15451829 | D6: ='Ratio Comparison'!G7 -> 0.28320312 | E6: RBC ✓ | F6: RBC 28.3% vs TD 15.4%
A7: Efficiency | B7: Efficiency Ratio | C7: ='Ratio Comparison'!D9 -> 0.62025759 | D7: ='Ratio Comparison'!G9 -> 0.5972726 | E7: RBC ✓ | F7: RBC 59.7% vs TD 62.0% (lower = better)
A8: Efficiency | B8: Rev/Assets | C8: ='Ratio Comparison'!D10 -> 0.027754564 | D8: ='Ratio Comparison'!G10 -> 0.025735167 | E8: Tie | F8: Both ~2.7–2.8%
A9: Asset Quality | B9: PCL/Loans | C9: ='Ratio Comparison'!D12 -> 0.0044791996 | D9: ='Ratio Comparison'!G12 -> 0.0033028697 | E9: RBC ✓ | F9: RBC 0.33% vs TD 0.46% (lower = better)
A10: Asset Quality | B10: Loans/Deposits | C10: ='Ratio Comparison'!D13 -> 0.74840388 | D10: ='Ratio Comparison'!G13 -> 0.76789425 | E10: Tie | F10: Both in healthy 74–77% range
A11: Capital | B11: Equity/Assets | C11: ='Ratio Comparison'!D15 -> 0.055874836 | D11: ='Ratio Comparison'!G15 -> 0.052698212 | E11: RBC ✓ | F11: RBC 5.27% vs TD 5.59% — both above floor
A12: Capital | B12: Payout Ratio | C12: ='Ratio Comparison'!D16 -> 0.84053382 | D12: ='Ratio Comparison'!G16 -> 0.48743842 | E12: RBC ✓ | F12: RBC 48.7% more sustainable than TD 84.1%
A13: Capital | B13: CF Quality | C13: ='Ratio Comparison'!D17 -> 1.875933 | D13: ='Ratio Comparison'!G17 -> 1.3634852 | E13: TD ✓ | F13: TD 1.88x vs RBC 1.36x — both strong
A16: SCORECARD SUMMARY
A17: TD Bank wins | E17: =COUNTIF(E4:E13,"TD ✓") -> 1
A18: RBC wins | E18: =COUNTIF(E4:E13,"RBC ✓") -> 7
A19: Ties | E19: =COUNTIF(E4:E13,"Tie") -> 2
A21: ANALYST RECOMMENDATION: RBC — OUTPERFORM | TD — HOLD

Sheet Visual Comparison
A1: TD Bank vs. RBC — Visual Comparison | FY2022–FY2024
B3: TD Bank | C3: RBC | K3: TD Bank | L3: RBC | Q3: TD Bank | R3: RBC
A4: FY2022 | B4: 0.152 | C4: 0.156 | J4: FY2022 | K4: 14523 | L4: 13163 | P4: FY2022 | Q4: 0.593 | R4: 0.59
A5: FY2023 | B5: 0.099 | C5: 0.142 | J5: FY2023 | K5: 10634 | L5: 14612 | P5: FY2023 | Q5: 0.589 | R5: 0.599
A6: FY2024 | B6: 0.082 | C6: 0.138 | J6: FY2024 | K6: 8842 | L6: 16240 | P6: FY2024 | Q6: 0.62 | R6: 0.597

Sheet Analyst Memo
B2: EQUITY RESEARCH — CANADIAN BANKING SECTOR
B3: TD Bank Group (TD:TSX) | Royal Bank of Canada (RY:TSX) | FY2024 Comparative Analysis
B4: Prepared by: Jeevan Dhaliwal, AFM Student, University of Waterloo | Date: May 2026
B6: RECOMMENDATION SUMMARY
B7: RBC — OUTPERFORM | TD Bank — HOLD
B9: EXECUTIVE SUMMARY
B10: FY2024 was a year of divergence for Canada's two largest banks. RBC delivered record earnings of $16.2B, driven by the HSBC Canada acquisition, strong wealth management performance, and disciplined expense management. TD, by contrast, faced a $3B USD regulatory penalty from US authorities for anti-money laundering (AML) control failures, which weighed heavily on reported net income ($8.8B vs. $10.6B in FY2023), compressed margins, and elevated its efficiency ratio above the 60% threshold.
B11: Across 10 financial metrics analyzed, RBC outperformed TD in 7 categories, with 2 ties and 1 category where TD led (operating CF / net income). At comparable revenue bases ($57.2B TD vs. $57.3B RBC), the profitability gap is striking: RBC converted 28.3% of revenue to net income while TD converted only 15.4%.
B13: KEY FINDINGS
B14: 1. PROFITABILITY GAP — RBC's ROE of 13.8% is nearly double TD's 8.2% in FY2024. This is not a structural difference — TD's ROE averaged 15.2% in FY2021–FY2023. The collapse is attributable to the AML fine and associated remediation costs, which added approximately $7B in non-interest expenses versus the prior year.
B15: 2. TD'S EFFICIENCY PROBLEM — TD's efficiency ratio rose to 62.0% in FY2024, above the 60% threshold considered healthy for Canadian banks. RBC maintained 59.7%. Every percentage point above 60% represents approximately $570MM in excess costs relative to revenue generated.
B16: 3. DIVIDEND SUSTAINABILITY CONCERN — TD's dividend payout ratio reached 84.1% of reported net income in FY2024, compared to RBC's 48.7%. While TD maintained its dividend ($4.08/share), the payout ratio at this level is unsustainable if earnings do not recover. RBC raised its dividend 4% to $1.48/quarter, backed by a comfortable payout ratio.
... B30: This memo was prepared for educational purposes as part of a personal finance project. It does not constitute investment advice.
